superpipe/__init__.py
superpipe/superpipe.py
superpipe/utils.py
superpipe-1.0.3.dist-info/LICENSE.txt
superpipe-1.0.3.dist-info/METADATA
superpipe-1.0.3.dist-info/WHEEL
superpipe-1.0.3.dist-info/top_level.txt
superpipe-1.0.3.dist-info/RECORD
