Metadata-Version: 2.1
Name: superpipe
Version: 1.0.3
Summary: UNKNOWN
Home-page: https://github.com/george-lewis/superpipe
Author: George Lewis
Author-email: georgejeffreylewis@gmail.com
License: UNKNOWN
Keywords: "python elixir"
Platform: UNKNOWN
Classifier: Programming Language :: Python :: 3
Classifier: License :: OSI Approved :: MIT License
Classifier: Operating System :: OS Independent
Requires-Python: >=3.5
License-File: LICENSE.txt
